README.md
setup.py
line_info/__init__.py
line_info/__main__.py
line_info/config.py
line_info/line_info.py
line_info.egg-info/PKG-INFO
line_info.egg-info/SOURCES.txt
line_info.egg-info/dependency_links.txt
line_info.egg-info/entry_points.txt
line_info.egg-info/not-zip-safe
line_info.egg-info/requires.txt
line_info.egg-info/top_level.txt
line_info/vcs_adapters/__init__.py
line_info/vcs_adapters/base.py
line_info/vcs_adapters/gitlab.py