Metadata-Version: 2.1
Name: line-info
Version: 0.0.1
Summary: CLI tool to fetch helpful info about line of code, such as issue number, related PRs, etc.
Home-page: https://github.com/MrMrRobat/line_info
Author: MrMrRobat
Author-email: appkiller16@gmail.com
License: License :: OSI Approved :: MIT License
Platform: UNKNOWN
Classifier: Programming Language :: Python
Classifier: Programming Language :: Python :: 3
Classifier: Operating System :: OS Independent
Requires-Python: >=3.6
